{"URL": "http://www.zhishijingsai.cn/zhishichanquan/", "question": "知识产权一般包括( )两部分。A、著作权,工业产权  B、著作权,专利权  C、著作权,商标权", "answer": "正确答案：A"}
{"URL": "http://www.zhishijingsai.cn/zhishichanquan/", "question": "《中华人民共和国专利法》于( )年3月12日通过,()年9月4日第一次修订,()年8月25日第二次修订。A、1984、1992、2000  B、1983、1993、1999  C、1984、1993、2000", "answer": "正确答案：A"}
{"URL": "http://www.zhishijingsai.cn/zhishichanquan/", "question": "世界贸易组织《与贸易有关的知识产权协定》( )是迄今为止最具综合性的知识产权多边协议,其中规定了()的知识产权。A、集成电路布图设计  B、实用新型  C、植物新品种", "answer": "正确答案：A"}
{"URL": "http://www.zhishijingsai.cn/zhishichanquan/", "question": "下面哪一项不属于由 TRIPS协定所规定的基本原则( )。A、国民待遇原则  B、最惠国待遇原则  C、公共健康原则", "answer": "正确答案：C"}
{"URL": "http://www.zhishijingsai.cn/zhishichanquan/", "question": "我国于( )成为世界知识产权组织WIPO)的正式成员国。A、29375  B、29740  C、31125", "answer": "正确答案：A"}
{"URL": "http://www.zhishijingsai.cn/zhishichanquan/", "question": "以下知识产权国际公约中,最早订立的是( )A、《保护工业产权巴黎公约》  B、《伯尔尼保护文学和艺术作品公约》  C、《世界版权公约》", "answer": "正确答案：A"}
{"URL": "http://www.zhishijingsai.cn/zhishichanquan/", "question": "在下列知识产权国际公约中,我国尚未加入的有( )。A、《保护表演者,录音制作者和广播组织的国际公约》(罗马公约)  B、《世界版权公约》  C、《国际植物新品种保护公约》", "answer": "正确答案：A"}
{"URL": "http://www.zhishijingsai.cn/zhishichanquan/", "question": "在商标方面的国际公约中,我国未加入的是( )。A、《商标国际注册马德里协定》  B、《商标国际注册马德里协定有关议定书》  C、《商标法律条约》", "answer": "正确答案：C"}
{"URL": "http://www.zhishijingsai.cn/zhishichanquan/", "question": "世界知识产权组织于1974年成为联合国组织系统的一个专门机构,其总部位于( )A、瑞士日内瓦  B、瑞士洛桑  C、美国纽约", "answer": "正确答案：A"}
{"URL": "http://www.zhishijingsai.cn/zhishichanquan/", "question": "据世界知识产权组织统计,专利文献记载了人类( )以上的新技术信息。A、0.9  B、0.6  C、科技局,专利商标局,特许厅", "answer": "正确答案：A"}
{"URL": "http://www.zhishijingsai.cn/zhishichanquan/", "question": "英国1624年制定的( )被称为”专利法之母”。A、专利法  B、垄断法  C、反托拉斯法", "answer": "正确答案：B"}
{"URL": "http://www.zhishijingsai.cn/zhishichanquan/", "question": "《保护工业产权巴黎公约》规定的”专利与我国专利法规定的专利是否外延相同( )。A、完全相同  B、前者大于后者  C、后者大于前者", "answer": "正确答案：C"}
{"URL": "http://www.zhishijingsai.cn/zhishichanquan/", "question": "甲比乙早一周完成了一个相同的发明,但乙比甲早一天提出了专利申请,若此发明符合授予专利的条件,请问应当将专利授予( )。A、甲  B、乙  C、甲,乙共有", "answer": "正确答案：B"}
{"URL": "http://www.zhishijingsai.cn/zhishichanquan/", "question": "根据我国专利法,职务发明创造的专利权应当属于( )。A、单位  B、发明人  C、单位与发明人共有", "answer": "正确答案：A"}
{"URL": "http://www.zhishijingsai.cn/zhishichanquan/", "question": "根据我国著作权法,职务作品的著作权一般情况下属于( )。A、单位  B、作者  C、单位与作者共有", "answer": "正确答案：B"}
{"URL": "http://www.zhishijingsai.cn/zhishichanquan/", "question": "产品发明专利和实用新型专利权人有权禁止他人未经其许可而为生产经营目的( )其专利产品。A、制造,使用,销售,进口  B、使用,许诺销售,销售,进口  C、制造,使用,许诺销售,销售,进口", "answer": "正确答案：C"}
{"URL": "http://www.zhishijingsai.cn/zhishichanquan/", "question": "外观设计的专利权人有权禁止他人未经其许可而为生产目的( )其外观设计专利产品。A、制造,销售,进口  B、制造,使用,销售  C、制造,使用,进口", "answer": "正确答案：A"}
{"URL": "http://www.zhishijingsai.cn/zhishichanquan/", "question": "我国专利法规定的授予发明专利和实用新型专利的三性条件是指( )。A、新颖性,创造性和实用性  B、新颖性,创造性和显著性  C、新颖性,独创性和实用性", "answer": "正确答案：A"}
{"URL": "http://www.zhishijingsai.cn/zhishichanquan/", "question": "在申请日以前6个月之内发生如下哪一种情形的,不丧失新颖性( )。A、在中国政府主办或者承认的国际展览会上首次展出的  B、在学术期刊上首次发表的  C、自己上传到互联网上的", "answer": "正确答案：A"}
{"URL": "http://www.zhishijingsai.cn/zhishichanquan/", "question": "根据我国专利法的规定,可以授予专利权的对象有( )。A、科学家发现了某种此前不为人知的物质  B、某人新创设了一种下棋方法  C、新的微生物品种", "answer": "正确答案：C"}
{"URL": "http://www.zhishijingsai.cn/zhishichanquan/", "question": "在下列主题中,( )可获得外观设计专利的保护。A、饮料  B、饮料的配方  C、饮料的包装盒", "answer": "正确答案：C"}
{"URL": "http://www.zhishijingsai.cn/zhishichanquan/", "question": "在发明或者实用新型专利申请文件中,用于说明专利保护范围的是( )。A、请求书  B、说明书  C、权利要求书", "answer": "正确答案：C"}
{"URL": "http://www.zhishijingsai.cn/zhishichanquan/", "question": "申请外观设计专利应当提交的文件是( )。A、请求书和图片或照片  B、说明书和图片或照片  C、权利要求书和图片或照片", "answer": "正确答案：A"}
{"URL": "http://www.zhishijingsai.cn/zhishichanquan/", "question": "所谓外国优先权是指在外国第一次提出专利或者商标注册申请之后又在中国就相同主题或者相同商品上的同一商标提出申请的,可以根据国际条约,双边协议或者互惠原则享有优先权,即以在外国的第一次申请作为在中国的申请日但享有优先权是受到时间限制的,根据我国专利法和著作权法的规定,该优先权期限分别是指( )。A、发明和实用新型是12个月,外观设计和商标是6个月  B、发明是12个月,实用新型,外观设计和商标是6个月  C、发明,实用新型和外观设计是12个月,商标是6个月", "answer": "正确答案：A"}
{"URL": "http://www.zhishijingsai.cn/zhishichanquan/", "question": "我国专利法规定,发明专利申请经初步审查认为符合要求的,( )公布。A、必须自申请日起满18个月才能  B、自申请日起满18个月即行公布,但可应申请人请求早日  C、只能应申请人请求", "answer": "正确答案：B"}
{"URL": "http://www.zhishijingsai.cn/zhishichanquan/", "question": "我国专利法规定必须进行实质审查的专利是( )。A、发明  B、发明和实用新型  C、发明,实用新型和外观设计", "answer": "正确答案：A"}
{"URL": "http://www.zhishijingsai.cn/zhishichanquan/", "question": "我国专利法规定的专利权保护期限是( )。A、自申请日起发明专利20年,实用新型和外观设计专利10年  B、自生效日起发明专利15年,实用新型和外观设计专利10年  C、自公告日起发明专利20年,实用新型和外观设计专利10年", "answer": "正确答案：A"}
{"URL": "http://www.zhishijingsai.cn/zhishichanquan/", "question": "修订后的专利法规定,就下列哪些( )专利,当事人对于专利复审委员会的复审决定或者宣告专利无效的决定不服而可向法院起诉()。A、发明  B、发明和实用新型  C、发明,实用新型和外观设计", "answer": "正确答案：C"}
{"URL": "http://www.zhishijingsai.cn/zhishichanquan/", "question": "在我国,当事人对于专利复审委员会的复审决定或者宣告专利无效的决定不服的,应当自收到通知之日起3个月内向( )起诉。A、北京市第一中级人民法院  B、北京市第二中级人民法院  C、北京市高级人民法院", "answer": "正确答案：A"}
{"URL": "http://www.zhishijingsai.cn/zhishichanquan/", "question": "我国专利法规定,转让专利申请权或者专利权的,当事人应当订立书面合同,并向国务院专利行政部门登记,由该部门予以公告、专利申请权或者专利权的转让自( )之日起生效。A、合同订立  B、登记  C、公告", "answer": "正确答案：B"}
{"URL": "http://www.zhishijingsai.cn/zhishichanquan/", "question": "某人完成一项发明后,从其个人利益最大化的角度看,合理的做法是( )。A、马上去申请专利  B、马上在一份专业杂志上发表  C、权衡利弊,确定究竟采取专利保护还是保持为商业秘密", "answer": "正确答案：C"}
{"URL": "http://www.zhishijingsai.cn/zhishichanquan/", "question": "管理专利工作的部门在专利权人请求其处理侵犯专利权的行为时,可以( )。A、认定侵权行为成立,责令停止侵权行为并确定赔偿数额  B、认定侵权行为成立,责令停止侵权行为并就赔偿数额进行调解  C、认定侵权行为成立,责令停止侵权行为,不得就赔偿问题进行调解或确定赔偿数额", "answer": "正确答案：B"}
{"URL": "http://www.zhishijingsai.cn/zhishichanquan/", "question": "专利权人应当自被授予专利权的当年开始缴纳年费,年费的计算是( )。A、每年相同的  B、递增的  C、递减的", "answer": "正确答案：B"}
{"URL": "http://www.zhishijingsai.cn/zhishichanquan/", "question": "以下哪种行为侵犯了专利权( )。A、为实验目的而使用他人有关专利  B、甲购买乙的专利产品,而后出售给丙,获利甚丰  C、甲和乙各自完成了相同的产品发明,乙通过申请获得了专利,但甲随后也开始生产销售自己的发明产品", "answer": "正确答案：C"}
{"URL": "http://www.zhishijingsai.cn/zhishichanquan/", "question": "《专利合作条约》(PCT)所建立的国际体系,使得在一个专利局以一种语言提交的一项申请(国际申请)在申请人指定的 成员国都具有相同的效力,以达到简化,经济之目的、我国成为 正式成员国的时间是()。A、33970  B、34335  C、34700", "answer": "正确答案：B"}
{"URL": "http://www.zhishijingsai.cn/zhishichanquan/", "question": "根据我国法律,下列侵犯知识产权的行为中不可能构成犯罪的有( )。A、擅自实施他人专利  B、假冒他人商标  C、盗版他人作品", "answer": "正确答案：A"}
{"URL": "http://www.zhishijingsai.cn/zhishichanquan/", "question": "转让注册商标的,商标注册人对其在同一或者类似商品上注册的相同或者近似的商标,( )。A、应当一并转让  B、可以分别转让  C、应当给予强制许可", "answer": "正确答案：A"}
{"URL": "http://www.zhishijingsai.cn/zhishichanquan/", "question": "在我国,知识产权民事纠纷案件一般应由( )管辖。A、基层人民法院  B、中级人民法院  C、高级人民法院", "answer": "正确答案：B"}
{"URL": "http://www.zhishijingsai.cn/zhishichanquan/", "question": "侵犯知识产权的诉讼时效为( ),自权利人或者利害关系人知道或者应当知道侵权行为之日起计算。A、1年  B、2年  C、4年", "answer": "正确答案：B"}
{"URL": "http://www.zhishijingsai.cn/zhishichanquan/", "question": "在美国,当事人对于专利纠纷案件一审判决不服的,只能上诉到( )。A、联邦巡回上诉法院  B、美国最高法院  C、哥伦比亚特区法院", "answer": "正确答案：A"}
{"URL": "http://www.zhishijingsai.cn/zhishichanquan/", "question": "美国甲公司对其发明在美国拥有一项专利,但它从未在中国申请并获得过专利,则其能否在中国得到保护( )。A、在中国同样可以得到专利保护  B、尽管没有专利但在中国可以得到商业秘密保护  C、不能得到任何保护", "answer": "正确答案：C"}
{"URL": "http://www.zhishijingsai.cn/zhishichanquan/", "question": "在我国,植物新品种权的保护期限是自( )起,藤本植物,林木,果树和观赏树木为20年,其他植物为15年。A、授权日  B、申请日  C、完成育种日", "answer": "正确答案：A"}
{"URL": "http://www.zhishijingsai.cn/zhishichanquan/", "question": "新的《海关知识产权保护条例》于( )开始实施。A、37956  B、37987  C、38047", "answer": "正确答案：C"}
{"URL": "http://www.zhishijingsai.cn/zhishichanquan/", "question": "两个以上的专利申请人分别、先后就同样的发明创造申请中国专利,专利权应授予( )。A、最先完成该发明创造的人  B、最先提出该专利申请的人  C、最先将该发明创造投入生产使用的人", "answer": "正确答案：B"}
{"URL": "http://www.zhishijingsai.cn/zhishichanquan/", "question": "被宣告无效的发明专利权,( )。A、自宣告该专利权无效之日起无效  B、自该专利申请之日起无效  C、自授予该专利权之日起无效。", "answer": "正确答案：C"}
{"URL": "http://www.zhishijingsai.cn/zhishichanquan/", "question": "一件发明或者实用新型专利申请应当限于( )发明或实用新型。A、一项  B、二项  C、二项以上", "answer": "正确答案：A"}
{"URL": "http://www.zhishijingsai.cn/zhishichanquan/", "question": "在我国,H公司在五年前获得了“一种新型控制器”产品的发明专利权,下列( )的行为侵犯了H公司的专利权?A、F商厦每年从H公司购买大量该专利产品后又将这些专利产品对外销售  B、在H公司专利申请日前已经每年生产1000件相同产品的G厂,今年又增加生产该产品3000件,其今年总产量达到4000件  C、J研究所为科学研究和实验目的而使用了二件H公司的该发明专利产品", "answer": "正确答案：B"}
{"URL": "http://www.zhishijingsai.cn/zhishichanquan/", "question": "上海东方通信高科技有限公司在上海向国家知识产权局上海专利代办处提交了三份专利申请,其专利申请的受理与审查单位是( )。A、国务院专利行政部门  B、上海市知识产权局  C、国家知识产权局上海专利代办处", "answer": "正确答案：A"}
{"URL": "http://www.zhishijingsai.cn/zhishichanquan/", "question": "我国发明专利权、实用新型专利权和外观设计专利权的保护期限分别是( )年。A、20年、10年、8年  B、20年、10年、10年  C、15年、8年、8年", "answer": "正确答案：B"}
{"URL": "http://www.zhishijingsai.cn/zhishichanquan/", "question": "江南化工研究所张某主要利用本所的设备、资金和技术资料完成的一项发明创造,该研究所与张某之间没有就该项发明创造的专利申请权达成过任何协议,该发明专利的申请权依法应属于( )。A、张某  B、江南化工研究所  C、江南化工研究所与张某共有", "answer": "正确答案：B"}
{"URL": "http://www.zhishijingsai.cn/zhishichanquan/", "question": "某研究所拥有以下成果,可以申请专利权的有( )。A、一种颈椎病治疗仪  B、一种颈椎病治疗方法  C、该治疗仪的客户销售名单", "answer": "正确答案：A"}
{"URL": "http://www.zhishijingsai.cn/zhishichanquan/", "question": "专利权人对国务院专利行政部门驳回申请的决定不服的,可以自收到申请之日起( ),向专利复审委员会请求复审。A、3个月内  B、6个月内  C、12个月内", "answer": "正确答案：A"}
{"URL": "http://www.zhishijingsai.cn/zhishichanquan/", "question": "依我国商标法的规定,商标专用权授予符合法定条件的( )。A、商标设计人  B、商标使用人  C、商标申请人", "answer": "正确答案：C"}
{"URL": "http://www.zhishijingsai.cn/zhishichanquan/", "question": "商品的通用名称,经使用取得显著特征并便于识别的,即产生第二含义的,( )。A、可以作为商标注册和使用  B、不能作为商标使用,也不能作为商标注册  C、可以作为商标注册,但不可以作为商标使用", "answer": "正确答案：A"}
{"URL": "http://www.zhishijingsai.cn/zhishichanquan/", "question": "我国商标法规定商标构成的要素有( )。A、文字、图形、字母、数字、气味、三维标志  B、文字、图形、字母、数字、音乐、三维标志  C、文字、图形、字母、数字、颜色组合、三维标志", "answer": "正确答案：C"}
{"URL": "http://www.zhishijingsai.cn/zhishichanquan/", "question": "转让注册商标的,受让人享有注册商标专用权的起始日为( )。A、转让协议公告之日  B、转让合同签订日  C、转让合同生效日", "answer": "正确答案：A"}
{"URL": "http://www.zhishijingsai.cn/zhishichanquan/", "question": "植物新品种,是指经过人工培育的或者对发现的野生植物加以开发,具备新颖性、( )、一致性和稳定性并有适当命名的植物品种。A、独创性  B、时间性  C、特异性", "answer": "正确答案：C"}
{"URL": "http://www.zhishijingsai.cn/zhishichanquan/", "question": "世界知识产权日是( )。A、44287  B、44312  C、44324", "answer": "正确答案：B"}
{"URL": "http://www.zhishijingsai.cn/zhishichanquan/", "question": "知识产权又被称为智慧财产权,它主要包括( )三大部分。A、专利、商标、集成电路设计  B、专利、商标、著作权  C、著作权、商标权、商业秘密", "answer": "正确答案：B"}
{"URL": "http://www.zhishijingsai.cn/zhishichanquan/", "question": "哪个国家率先提出“知识产权战略立国”?( )A、美国  B、日本  C、英国", "answer": "正确答案：B"}
{"URL": "http://www.zhishijingsai.cn/zhishichanquan/", "question": "“专利制度是给天才之火浇上利益之油”这句名言出自( )A、丘吉尔  B、林肯  C、约翰逊", "answer": "正确答案：B"}
{"URL": "http://www.zhishijingsai.cn/zhishichanquan/", "question": "国务院吴仪副总理在( )提出我国要实施知识产权战略。A、2004年  B、2003年  C、2002年", "answer": "正确答案：A"}
{"URL": "http://www.zhishijingsai.cn/zhishichanquan/", "question": "世界上最早建立专利制度的国家是( )。A、英国  B、法国  C、威尼斯共和国", "answer": "正确答案：C"}
{"URL": "http://www.zhishijingsai.cn/zhishichanquan/", "question": "专利法的本质是( )。A、对发明创造专利权提供法律保护  B、发明创造的推广应用  C、鼓励成名成家", "answer": "正确答案：A"}
{"URL": "http://www.zhishijingsai.cn/zhishichanquan/", "question": "新修改的专利法突出强调了专利立法要为( )服务。A、技术跨越发展  B、科技进步与创新  C、引进技术", "answer": "正确答案：B"}
{"URL": "http://www.zhishijingsai.cn/zhishichanquan/", "question": "我国的专利申请由下列哪一机构批准?( )A、省专利管理部门  B、市专利管理部门  C、国家知识产权局专利局", "answer": "正确答案：C"}
{"URL": "http://www.zhishijingsai.cn/zhishichanquan/", "question": "某单位职工拟就一项非职务发明申请专利( )。A、须经单位领导同意  B、可以直接向国家知识产权局专利局递交申请  C、须经专家鉴定或有关部门审批", "answer": "正确答案：B"}
{"URL": "http://www.zhishijingsai.cn/zhishichanquan/", "question": "我国专利法规定,两个或两个以上的专利申请人就相同内容先后提出申请,谁有权获得专利权( )。A、第一个完成发明创造的人  B、第一个提出专利申请的人  C、两人共同拥有", "answer": "正确答案：B"}
{"URL": "http://www.zhishijingsai.cn/zhishichanquan/", "question": "如果专利申请文件是邮寄的,申请日应当如何确定?( )A、以专利局收到日为申请日  B、以寄出的邮戳日为申请日  C、以寄达的邮戳日为申请日", "answer": "正确答案：B"}
{"URL": "http://www.zhishijingsai.cn/zhishichanquan/", "question": "对于符合专利法规定的专利申请,由国务院专利行政部门颁发( )。A、发明证书  B、专利证书  C、科技成果证书", "answer": "正确答案：B"}
{"URL": "http://www.zhishijingsai.cn/zhishichanquan/", "question": "我国发明专利权的保护期限为几年?( )A、10年  B、15年  C、20年", "answer": "正确答案：C"}
{"URL": "http://www.zhishijingsai.cn/zhishichanquan/", "question": "我国实用新型和外观设计专利权的保护期限为几年?( )A、10年  B、15年  C、20年", "answer": "正确答案：A"}
{"URL": "http://www.zhishijingsai.cn/zhishichanquan/", "question": "发明或实用新型专利权的保护范围以哪一项内容为准( )A、说明书  B、权利要求书  C、请求书", "answer": "正确答案：B"}
{"URL": "http://www.zhishijingsai.cn/zhishichanquan/", "question": "专利申请优先权是指申请人就同一发明创造第一次提出专利申请后,在规定的期限内又向他国提出申请的,可享有第一次提出的( )的权利。A、申请日  B、授权日  C、发明日", "answer": "正确答案：A"}
{"URL": "http://www.zhishijingsai.cn/zhishichanquan/", "question": "美国甲公司对其发明在美国拥有一项专利,但它从未在中国申请并获得过专利,则其能否在中国得到保护?( )。A、在中国同样可以得到专利保护  B、尽管没有专利,但在中国可以得到商业秘底  C、不能得到任何保护", "answer": "正确答案：C"}
{"URL": "http://www.zhishijingsai.cn/zhishichanquan/", "question": "我国专利法规定发明专利权的生效日期是( )A、发给专利证书之日  B、专利局作出授予专利权决定之日  C、专利权公告之日", "answer": "正确答案：C"}
{"URL": "http://www.zhishijingsai.cn/zhishichanquan/", "question": "王先生认为某项专利的授予不符合《中华人民共和国专利法》的有关规定,他应该请求什么机关宣告该专利权无效?( )。A、专利复审委员会  B、市知识产权局  C、中级人民法院", "answer": "正确答案：A"}
{"URL": "http://www.zhishijingsai.cn/zhishichanquan/", "question": "某公司在自己生产的产品上随意打上一个不存在的专利号,属于( )。A、假冒专利行为  B、冒充专利行为  C、盗窃专利行为", "answer": "正确答案：B"}
{"URL": "http://www.zhishijingsai.cn/zhishichanquan/", "question": "授予专利权的发明和实用新型应当具备( )条件A、新颖性、创造性、实用性  B、新颖性、突破性、实用性  C、新颖性、创造性、突破性", "answer": "正确答案：A"}
{"URL": "http://www.zhishijingsai.cn/zhishichanquan/", "question": "在我国审批专利的原则是?( )。A、先申请原则  B、先发明原则  C、先使用原则", "answer": "正确答案：A"}
{"URL": "http://www.zhishijingsai.cn/zhishichanquan/", "question": "申请专利时申请人应当向专利局提交申请文件一式( )。A、两份  B、三份  C、一份", "answer": "正确答案：A"}
{"URL": "http://www.zhishijingsai.cn/zhishichanquan/", "question": "甲研究所接受乙企业的委托完成一项有关污水处理装置发明创造。在双方事前无协议约定的情况下,则专利申请权应属于( )。A、甲研究所  B、乙企业  C、应属于甲乙共有", "answer": "正确答案：A"}
{"URL": "http://www.zhishijingsai.cn/zhishichanquan/", "question": "甲公司指派其研究人员乙和丙共同研究开发一项技术,该技术开发完成后,甲公司决定就该项技术申请专利。在填写专利申请文件时“发明人”一栏应当填写( )。A、甲公司的名称  B、乙或者丙的姓名  C、乙和丙的姓名", "answer": "正确答案：C"}
{"URL": "http://www.zhishijingsai.cn/zhishichanquan/", "question": "某人完成一项发明后,如果该发明容易为他人所仿造剽窃,那么请问从其个人利益最大化的角度看,合理的做法是( )。A、马上去申请专利  B、马上在一份专业杂志上发表  C、将其保持为商业保密", "answer": "正确答案：A"}
{"URL": "http://www.zhishijingsai.cn/zhishichanquan/", "question": "专利申请权和专利权转让时,必须办理的手续是什么?( )A、订立书面合同  B、经市知识产权局批准  C、订立书面合同并经国务院专利行政部门登记", "answer": "正确答案：C"}
{"URL": "http://www.zhishijingsai.cn/zhishichanquan/", "question": "国务院专利行政部门收到发明专利申请后,经初步审查认为符合本法要求的,自申请日起满多少个月,即行公布?( )A、18个月  B、12个月  C、6个月", "answer": "正确答案：A"}
{"URL": "http://www.zhishijingsai.cn/zhishichanquan/", "question": "发明专利申请自申请日起多少年内,专利局可以根据申请人随时提出的请求,对其进行实质审查?( )A、1年  B、2年  C、3年", "answer": "正确答案：C"}
{"URL": "http://www.zhishijingsai.cn/zhishichanquan/", "question": "专利申请被驳回,申请人不服,三个月内可以向哪个机构请求复审?( )。A、专利局专利复审委员会  B、人民法院  C、地方知识产权局", "answer": "正确答案：A"}
{"URL": "http://www.zhishijingsai.cn/zhishichanquan/", "question": "中学生李某制作了一项小发明,一般而言,他可在( )申请专利A、18岁以后  B、小发明制作完成  C、学校同意以后", "answer": "正确答案：B"}
{"URL": "http://www.zhishijingsai.cn/zhishichanquan/", "question": "在我国就新型电视机的制造方法可以提出( )。A、发明、外观设计专利申请  B、发明、实用新型、外观设计专利申请  C、发明专利申请,不能申请实用新型或外观设计专利", "answer": "正确答案：C"}
{"URL": "http://www.zhishijingsai.cn/zhishichanquan/", "question": "我国专利法规定,外观设计专利权的保护范围( )。A、以外观设计专利产品为准  B、以图片和照片为准  C、以表示在图片或者照片中的该外观设计专利产品为准", "answer": "正确答案：C"}
{"URL": "http://www.zhishijingsai.cn/zhishichanquan/", "question": "甲、乙、丙三方合作开发并共同完成了一项发明创造,三方又未约定专利权归属的,当甲方不同意申请专利时,( )。A、乙方和丙方都可以单独申请专利  B、乙丙双方可以以甲、乙、丙三方的名义共同申请专利  C、乙方、丙方都不能申请专利", "answer": "正确答案：C"}
{"URL": "http://www.zhishijingsai.cn/zhishichanquan/", "question": "被宣告无效的发明专利权,( )。A、自宣告该专利权无效之日起无效  B、自该专利申请之日起无效  C、自授予该专利权之日起无效。", "answer": "正确答案：C"}
{"URL": "http://www.zhishijingsai.cn/zhishichanquan/", "question": "假冒他人专利,情节严重的,处多少年以下有期徒刑或拘役?( )A、1年  B、3年  C、5年", "answer": "正确答案：B"}
{"URL": "http://www.zhishijingsai.cn/zhishichanquan/", "question": "从2003年10月1日起,专利申请号由原有的8位数升至( )位数。A、13  B、12  C、10", "answer": "正确答案：B"}
{"URL": "http://www.zhishijingsai.cn/zhishichanquan/", "question": "发明专利申请公布后至专利权授予前使用这发明未支付适当使用费的,专利权人要求支付使用费的诉讼时效为( )。A、1年  B、2年  C、3年", "answer": "正确答案：B"}
{"URL": "http://www.zhishijingsai.cn/zhishichanquan/", "question": "对冒充专利行为,( )有权责令其改正并予公告。A、管理专利工作的部门  B、人民法院  C、工商行政管理部门", "answer": "正确答案：A"}
{"URL": "http://www.zhishijingsai.cn/zhishichanquan/", "question": "在中国,美国和日本受理专利申请的机构分别为()。A、知识产权局,专利商标局,特许厅  B、知识产权局,专利局,发明协会  C、科技局,专利商标局,特许厅", "answer": "正确答案：A"}
{"URL": "http://www.zhishijingsai.cn/zhishichanquan/", "question": "国务院专利行政部门发出授予专利权的通知后,申请人应当自收到通知之日起( )个月内办理缴纳专利第一次年费和登记费等手续。A、1  B、2  C、3", "answer": "正确答案：B"}
{"URL": "http://www.zhishijingsai.cn/zhishichanquan/", "question": "下列文件被认为是世界上第一部版权法的是( )。A、1709年英国的《安娜女王法》  B、1890年美国的《谢尔曼反不正当竞争法》  C、世贸组织的《知识产权协定》D、1900的《巴黎公约》", "answer": "正确答案：A"}
{"URL": "http://www.zhishijingsai.cn/zhishichanquan/", "question": "说知识产权是( ),比较全面。A、活着的人的智力成果  B、自然人的智力成果  C、自然人或法人的智力成果D、公民的智力成果", "answer": "正确答案：C"}
{"URL": "http://www.zhishijingsai.cn/zhishichanquan/", "question": "专利权的地域性是指在( )拥有法律保护。A、权利人所在的民族区域  B、申请地所在的国家或者地区  C、权利人所在国家的建交国家或地区D、权利人的国籍国或地区", "answer": "正确答案：B"}
{"URL": "http://www.zhishijingsai.cn/zhishichanquan/", "question": "下列选项,哪项中含有保护期限不受时间限制的知识产权?( )A、商标权  B、著作权  C、实用新型专利权D、发明专利权", "answer": "正确答案：B"}
{"URL": "http://www.zhishijingsai.cn/zhishichanquan/", "question": "狭义的知识产权包括( )。A、工业产权和版权  B、著作权和商标权  C、专利权和著作权D、邻接权和集成电路布图设计权", "answer": "正确答案：A"}
{"URL": "http://www.zhishijingsai.cn/zhishichanquan/", "question": "作者的传播权包括( )。A、放映权和展览权  B、人身权和财产权  C、排他权和独占权D、表演者权、录制者权广播组织权、出版者权", "answer": "正确答案：D"}
{"URL": "http://www.zhishijingsai.cn/zhishichanquan/", "question": "以下属于知识产权范围的是( )。A、石子游戏规则  B、数学累加方法  C、作家头脑中的灵感D、舞蹈演员的表演", "answer": "正确答案：D"}
{"URL": "http://www.zhishijingsai.cn/zhishichanquan/", "question": "以下属于知识产权性质范围的是( )。A、可触摸性  B、不可复制性  C、无形性D、永久性", "answer": "正确答案：C"}
{"URL": "http://www.zhishijingsai.cn/zhishichanquan/", "question": "工业产权中的创造性成果权包括( )。A、发明专利权、使用新型权、外观设计权  B、商标权、商号权  C、服务标记权、货源标记权、原产地名称权D、制止不正当竞争权", "answer": "正确答案：A"}
{"URL": "http://www.zhishijingsai.cn/zhishichanquan/", "question": "以下属于边缘保护对象的是( )。A、外观设计权  B、商标权  C、著作权D、专利权", "answer": "正确答案：A"}
{"URL": "http://www.zhishijingsai.cn/zhishichanquan/", "question": "广义的版权分为( )。A、人身权和邻接权  B、作品的创作者权、作品的传播权  C、财产权和邻接权D、人身权和表演者权", "answer": "正确答案：B"}
{"URL": "http://www.zhishijingsai.cn/zhishichanquan/", "question": "知识产权公约协议中,1994年4月15签署、1995年1月1日生效的是那一协议( )。A、尼泊尔公约  B、巴黎公约  C、与贸易有关的知识产权D、世界知识产权组织公约", "answer": "正确答案：C"}
{"URL": "http://www.zhishijingsai.cn/zhishichanquan/", "question": "以下不是我国民法通则中保护的知识产权形式的是( )。A、著作权、专利权  B、商标权、发明权  C、发现权及其他科技成果权D、制止不正当竞争权", "answer": "正确答案：D"}
